{
  "teams": [
    {
      "name": "Manchester United",
      "logo": "https://upload.wikimedia.org/wikipedia/en/thumb/7/7a/Manchester_United_FC_crest.svg/1200px-Manchester_United_FC_crest.svg.png",
      "points": "44",
      "id": 3
    },
    {
      "name": "Arsenal FC",
      "logo": "https://upload.wikimedia.org/wikipedia/en/thumb/5/53/Arsenal_FC.svg/1200px-Arsenal_FC.svg.png",
      "points": "123",
      "id": 4
    },
    {
      "name": "FC Barcelona",
      "logo": "https://upload.wikimedia.org/wikipedia/en/thumb/4/47/FC_Barcelona_%28crest%29.svg/1200px-FC_Barcelona_%28crest%29.svg.png",
      "points": "91",
      "id": 5
    },
    {
      "name": "Bayern Munich",
      "logo": "https://upload.wikimedia.org/wikipedia/commons/thumb/1/1b/FC_Bayern_M%C3%BCnchen_logo_%282017%29.svg/1200px-FC_Bayern_M%C3%BCnchen_logo_%282017%29.svg.png",
      "points": "55",
      "id": 7
    },
    {
      "name": "Manchester City",
      "logo": "https://upload.wikimedia.org/wikipedia/en/thumb/e/eb/Manchester_City_FC_badge.svg/1200px-Manchester_City_FC_badge.svg.png",
      "points": "41",
      "id": 8
    },
    {
      "name": "Real Madrid",
      "logo": "https://upload.wikimedia.org/wikipedia/en/thumb/5/56/Real_Madrid_CF.svg/1200px-Real_Madrid_CF.svg.png",
      "points": "45",
      "id": 9
    },
    {
      "name": "Chelsea FC",
      "logo": "https://upload.wikimedia.org/wikipedia/en/thumb/c/cc/Chelsea_FC.svg/1200px-Chelsea_FC.svg.png",
      "points": "44",
      "id": 10
    }
  ]
}